plsa/__init__.py
plsa/corpus.py
plsa/pipeline.py
plsa/preprocessors.py
plsa/visualize.py
plsa/algorithms/__init__.py
plsa/algorithms/base.py
plsa/algorithms/conditional_plsa.py
plsa/algorithms/plsa.py
plsa/algorithms/result.py
plsa-0.6.0.dist-info/LICENSE
plsa-0.6.0.dist-info/METADATA
plsa-0.6.0.dist-info/WHEEL
plsa-0.6.0.dist-info/top_level.txt
plsa-0.6.0.dist-info/RECORD
